odoo/addons/ssi_service_quotation/README.rst
odoo/addons/ssi_service_quotation/__init__.py
odoo/addons/ssi_service_quotation/__manifest__.py
odoo/addons/ssi_service_quotation/data/approval_template_data.xml
odoo/addons/ssi_service_quotation/data/ir_sequence_data.xml
odoo/addons/ssi_service_quotation/data/policy_template_data.xml
odoo/addons/ssi_service_quotation/data/sequence_template_data.xml
odoo/addons/ssi_service_quotation/models/__init__.py
odoo/addons/ssi_service_quotation/models/service_contract.py
odoo/addons/ssi_service_quotation/models/service_quotation.py
odoo/addons/ssi_service_quotation/models/service_quotation_fix_item.py
odoo/addons/ssi_service_quotation/models/service_quotation_fix_item_payment_term.py
odoo/addons/ssi_service_quotation/models/service_quotation_fix_item_payment_term_detail.py
odoo/addons/ssi_service_quotation/security/ir.model.access.csv
odoo/addons/ssi_service_quotation/security/ir_module_category_data.xml
odoo/addons/ssi_service_quotation/security/ir_rule_data.xml
odoo/addons/ssi_service_quotation/security/res_group_data.xml
odoo/addons/ssi_service_quotation/static/description/icon.png
odoo/addons/ssi_service_quotation/views/service_contract_views.xml
odoo/addons/ssi_service_quotation/views/service_quotation_views.xml
odoo/addons/ssi_service_quotation/wizards/__init__.py
odoo/addons/ssi_service_quotation/wizards/copy_quotation_term.py
odoo/addons/ssi_service_quotation/wizards/copy_quotation_term_views.xml
odoo14_addon_ssi_service_quotation-14.0.1.15.0.dist-info/METADATA
odoo14_addon_ssi_service_quotation-14.0.1.15.0.dist-info/WHEEL
odoo14_addon_ssi_service_quotation-14.0.1.15.0.dist-info/top_level.txt
odoo14_addon_ssi_service_quotation-14.0.1.15.0.dist-info/RECORD
